[
  {
    "id": "1875127972342137267",
    "text": "@bluegwei 21%",
    "username": "Hy_Purr_liquid",
    "timestamp": 1735900321000,
    "createdAt": "2025-01-03T10:32:01.000Z",
    "isReply": true,
    "isRetweet": false,
    "likes": 1,
    "retweetCount": 0,
    "replies": 0,
    "photos": [],
    "videos": [],
    "urls": [],
    "permanentUrl": "https://twitter.com/Hy_Purr_liquid/status/1875127972342137267",
    "inReplyToStatusId": "1875111518465139133",
    "hashtags": []
  },
  {
    "id": "1875115491045556716",
    "text": "@Crave132 @Pickle_cRypto But spot at $10 short hype $25 yiute effectively selling at $25",
    "username": "Hy_Purr_liquid",
    "timestamp": 1735897345000,
    "createdAt": "2025-01-03T09:42:25.000Z",
    "isReply": true,
    "isRetweet": false,
    "likes": 0,
    "retweetCount": 0,
    "replies": 0,
    "photos": [],
    "videos": [],
    "urls": [],
    "permanentUrl": "https://twitter.com/Hy_Purr_liquid/status/1875115491045556716",
    "inReplyToStatusId": "1874797868311294189",
    "hashtags": []
  },
  {
    "id": "1875107516344066510",
    "text": "@ColdBloodShill Luna was scam, Hype will be top 5 token within 1-2 years.",
    "username": "Hy_Purr_liquid",
    "timestamp": 1735895444000,
    "createdAt": "2025-01-03T09:10:44.000Z",
    "isReply": true,
    "isRetweet": false,
    "likes": 10,
    "retweetCount": 0,
    "replies": 1,
    "photos": [],
    "videos": [],
    "urls": [],
    "permanentUrl": "https://twitter.com/Hy_Purr_liquid/status/1875107516344066510",
    "inReplyToStatusId": "1875087101404066264",
    "hashtags": []
  },
  {
    "id": "1875104080231821692",
    "text": "Some weekly Hyperliquid stats I'm going to keep an eye on starting  Jan 3, 2025  16:47\nBridged USDC                         $2,071,177,360\nCirculating hype staked              91,983,704  (27.5%)\nAssistance Fund Hype                   11,813,617\nHLP…",
    "username": "Hy_Purr_liquid",
    "timestamp": 1735894625000,
    "createdAt": "2025-01-03T08:57:05.000Z",
    "isReply": false,
    "isRetweet": false,
    "likes": 29,
    "retweetCount": 1,
    "replies": 3,
    "photos": [],
    "videos": [],
    "urls": [],
    "permanentUrl": "https://twitter.com/Hy_Purr_liquid/status/1875104080231821692",
    "hashtags": []
  },
  {
    "id": "1875042213778128941",
    "text": "@100xStake @ravent898 @Hypurrfun Bonded already",
    "username": "Hy_Purr_liquid",
    "timestamp": 1735879875000,
    "createdAt": "2025-01-03T04:51:15.000Z",
    "isReply": true,
    "isRetweet": false,
    "likes": 0,
    "retweetCount": 0,
    "replies": 1,
    "photos": [],
    "videos": [],
    "urls": [],
    "permanentUrl": "https://twitter.com/Hy_Purr_liquid/status/1875042213778128941",
    "inReplyToStatusId": "1874862514309406753",
    "hashtags": []
  },
  {
    "id": "1874953722943668464",
    "text": "Mon marketcap $140 million evm coin just listed on hyperliquid",
    "username": "Hy_Purr_liquid",
    "timestamp": 1735858777000,
    "createdAt": "2025-01-02T22:59:37.000Z",
    "isReply": false,
    "isRetweet": false,
    "likes": 7,
    "retweetCount": 1,
    "replies": 1,
    "photos": [],
    "videos": [],
    "urls": [],
    "permanentUrl": "https://twitter.com/Hy_Purr_liquid/status/1874953722943668464",
    "quotedStatusId": "1874875326486167552",
    "hashtags": []
  },
  {
    "id": "1874618840212218322",
    "text": "@jessepollak @ethereum @base base is coinbase \na VC owned L2",
    "username": "Hy_Purr_liquid",
    "timestamp": 1735778934000,
    "createdAt": "2025-01-02T00:48:54.000Z",
    "isReply": true,
    "isRetweet": false,
    "likes": 1,
    "retweetCount": 0,
    "replies": 0,
    "photos": [],
    "videos": [],
    "urls": [],
    "permanentUrl": "https://twitter.com/Hy_Purr_liquid/status/1874618840212218322",
    "inReplyToStatusId": "1874555410365194306",
    "hashtags": []
  },
  {
    "id": "1874617365549535672",
    "text": "@IDrawCharts it's a VC chain, really no benefit to users to use it when Coinbase gobbles up all the profits made from the activity",
    "username": "Hy_Purr_liquid",
    "timestamp": 1735778583000,
    "createdAt": "2025-01-02T00:43:03.000Z",
    "isReply": true,
    "isRetweet": false,
    "likes": 1,
    "retweetCount": 0,
    "replies": 0,
    "photos": [],
    "videos": [],
    "urls": [],
    "permanentUrl": "https://twitter.com/Hy_Purr_liquid/status/1874617365549535672",
    "inReplyToStatusId": "1874615764151635979",
    "hashtags": []
  },
  {
    "id": "1874599292901757112",
    "text": "Hyperliquid has rarely done anything in a standard way, would not be surprised if they bake in additional rewards to staking down the track.",
    "username": "Hy_Purr_liquid",
    "timestamp": 1735774274000,
    "createdAt": "2025-01-01T23:31:14.000Z",
    "isReply": false,
    "isRetweet": false,
    "likes": 37,
    "retweetCount": 5,
    "replies": 1,
    "photos": [],
    "videos": [],
    "urls": [],
    "permanentUrl": "https://twitter.com/Hy_Purr_liquid/status/1874599292901757112",
    "quotedStatusId": "1874524787625923057",
    "hashtags": []
  },
  {
    "id": "1874583795418230919",
    "text": "@0xJonan @stevenyuntcap Said it in an interview",
    "username": "Hy_Purr_liquid",
    "timestamp": 1735770579000,
    "createdAt": "2025-01-01T22:29:39.000Z",
    "isReply": true,
    "isRetweet": false,
    "likes": 1,
    "retweetCount": 0,
    "replies": 0,
    "photos": [],
    "videos": [],
    "urls": [],
    "permanentUrl": "https://twitter.com/Hy_Purr_liquid/status/1874583795418230919",
    "inReplyToStatusId": "1874574026666086605",
    "hashtags": []
  },
  {
    "id": "1874562658286108995",
    "text": "@stevenyuntcap I remember Jeff saying coin trading fees don't have to he burned there are options there and how big does the AF get before it becomes pointless sending fees to it",
    "username": "Hy_Purr_liquid",
    "timestamp": 1735765540000,
    "createdAt": "2025-01-01T21:05:40.000Z",
    "isReply": true,
    "isRetweet": false,
    "likes": 3,
    "retweetCount": 1,
    "replies": 2,
    "photos": [],
    "videos": [],
    "urls": [],
    "permanentUrl": "https://twitter.com/Hy_Purr_liquid/status/1874562658286108995",
    "inReplyToStatusId": "1874524787625923057",
    "hashtags": []
  },
  {
    "id": "1874404985380942035",
    "text": "@oldmankotaro If sol hits 500(which it wont) then hypes going to 200",
    "username": "Hy_Purr_liquid",
    "timestamp": 1735727947000,
    "createdAt": "2025-01-01T10:39:07.000Z",
    "isReply": true,
    "isRetweet": false,
    "likes": 5,
    "retweetCount": 0,
    "replies": 0,
    "photos": [],
    "videos": [],
    "urls": [],
    "permanentUrl": "https://twitter.com/Hy_Purr_liquid/status/1874404985380942035",
    "inReplyToStatusId": "1874235517174530463",
    "hashtags": []
  },
  {
    "id": "1874403473250488465",
    "text": "Hyperliquid has reached 1 trillion volume in 18 months with a single usdc bridge",
    "username": "Hy_Purr_liquid",
    "timestamp": 1735727587000,
    "createdAt": "2025-01-01T10:33:07.000Z",
    "isReply": false,
    "isRetweet": false,
    "likes": 34,
    "retweetCount": 3,
    "replies": 3,
    "photos": [],
    "videos": [],
    "urls": [],
    "permanentUrl": "https://twitter.com/Hy_Purr_liquid/status/1874403473250488465",
    "quotedStatusId": "1874388852342996997",
    "hashtags": []
  },
  {
    "id": "1874307291593531795",
    "text": "@fiege_max Decentralisation isnt important unless it affects my drift bags",
    "username": "Hy_Purr_liquid",
    "timestamp": 1735704655000,
    "createdAt": "2025-01-01T04:10:55.000Z",
    "isReply": true,
    "isRetweet": false,
    "likes": 2,
    "retweetCount": 0,
    "replies": 1,
    "photos": [],
    "videos": [],
    "urls": [],
    "permanentUrl": "https://twitter.com/Hy_Purr_liquid/status/1874307291593531795",
    "inReplyToStatusId": "1874080731909198109",
    "hashtags": []
  },
  {
    "id": "1874245295988760774",
    "text": "@0xKNL__ tagged bitch https://t.co/vrHszRf4Co",
    "username": "Hy_Purr_liquid",
    "timestamp": 1735689875000,
    "createdAt": "2025-01-01T00:04:35.000Z",
    "isReply": true,
    "isRetweet": false,
    "likes": 4,
    "retweetCount": 0,
    "replies": 1,
    "photos": [
      {
        "id": "1874245287474323462",
        "url": "https://pbs.twimg.com/media/GgKoKKXbYAYl9CM.png"
      }
    ],
    "videos": [],
    "urls": [],
    "permanentUrl": "https://twitter.com/Hy_Purr_liquid/status/1874245295988760774",
    "inReplyToStatusId": "1874235802181656769",
    "hashtags": []
  },
  {
    "id": "1874004142005641520",
    "text": "@0xOmnia Nearly 20% of all circulating hype is being staked. When liquid staking becomes available, I'd expect that to double. Will be a lot less hype for sale",
    "username": "Hy_Purr_liquid",
    "timestamp": 1735632379000,
    "createdAt": "2024-12-31T08:06:19.000Z",
    "isReply": true,
    "isRetweet": false,
    "likes": 6,
    "retweetCount": 0,
    "replies": 1,
    "photos": [],
    "videos": [],
    "urls": [],
    "permanentUrl": "https://twitter.com/Hy_Purr_liquid/status/1874004142005641520",
    "inReplyToStatusId": "1873759440886714774",
    "hashtags": []
  },
  {
    "id": "1873861128759230569",
    "text": "@stevenyuntcap What will happen to slashed tokens?",
    "username": "Hy_Purr_liquid",
    "timestamp": 1735598282000,
    "createdAt": "2024-12-30T22:38:02.000Z",
    "isReply": true,
    "isRetweet": false,
    "likes": 4,
    "retweetCount": 0,
    "replies": 2,
    "photos": [],
    "videos": [],
    "urls": [],
    "permanentUrl": "https://twitter.com/Hy_Purr_liquid/status/1873861128759230569",
    "inReplyToStatusId": "1873785440660304327",
    "hashtags": []
  },
  {
    "id": "1873715205685063769",
    "text": "Reason I am hyper bullish is the hyperliquid team has an unfair advantage, it's an uneven playing field. They are an NBA allstar team playing in the under 18 amateur league.\nWhere did they get such a big advantage?\n\nBefore Hyperliquid, the team ran a highly profitable crypto… https://t.co/tyIV6m6UUs",
    "username": "Hy_Purr_liquid",
    "timestamp": 1735563491000,
    "createdAt": "2024-12-30T12:58:11.000Z",
    "isReply": false,
    "isRetweet": false,
    "likes": 55,
    "retweetCount": 5,
    "replies": 5,
    "photos": [
      {
        "id": "1873710172088287232",
        "url": "https://pbs.twimg.com/media/GgDBeWNbwAA9GEl.png"
      }
    ],
    "videos": [],
    "urls": [],
    "permanentUrl": "https://twitter.com/Hy_Purr_liquid/status/1873715205685063769",
    "hashtags": []
  },
  {
    "id": "1873696860390768981",
    "text": "Hyperliquid continues to ship faster than any other chain. Staking is here https://t.co/aPly8ZdPwa",
    "username": "Hy_Purr_liquid",
    "timestamp": 1735559117000,
    "createdAt": "2024-12-30T11:45:17.000Z",
    "isReply": false,
    "isRetweet": false,
    "likes": 105,
    "retweetCount": 7,
    "replies": 14,
    "photos": [
      {
        "id": "1873696747035504640",
        "url": "https://pbs.twimg.com/media/GgC1Q5_bMAAZjwG.jpg"
      }
    ],
    "videos": [],
    "urls": [],
    "permanentUrl": "https://twitter.com/Hy_Purr_liquid/status/1873696860390768981",
    "hashtags": []
  },
  {
    "id": "1873696475257143398",
    "text": "It looks like hype staking is now available, an extra 23 million has been staked https://t.co/5Ni3PGKocu",
    "username": "Hy_Purr_liquid",
    "timestamp": 1735559025000,
    "createdAt": "2024-12-30T11:43:45.000Z",
    "isReply": false,
    "isRetweet": false,
    "likes": 33,
    "retweetCount": 3,
    "replies": 0,
    "photos": [
      {
        "id": "1873696408311898112",
        "url": "https://pbs.twimg.com/media/GgC09MJbIAA0ZNR.jpg"
      }
    ],
    "videos": [],
    "urls": [],
    "permanentUrl": "https://twitter.com/Hy_Purr_liquid/status/1873696475257143398",
    "hashtags": []
  },
  {
    "id": "1873695856786067492",
    "text": "Blocks have been validated by the new validators, Hyperliquid is officially decentralised https://t.co/j2iDEykCa2",
    "username": "Hy_Purr_liquid",
    "timestamp": 1735558878000,
    "createdAt": "2024-12-30T11:41:18.000Z",
    "isReply": false,
    "isRetweet": false,
    "likes": 74,
    "retweetCount": 18,
    "replies": 1,
    "photos": [
      {
        "id": "1873695595007004672",
        "url": "https://pbs.twimg.com/media/GgC0N2WbUAArk6Z.jpg"
      }
    ],
    "videos": [],
    "urls": [],
    "permanentUrl": "https://twitter.com/Hy_Purr_liquid/status/1873695856786067492",
    "hashtags": []
  },
  {
    "id": "1873164352184107149",
    "text": "@cole0x If you’re a guy in your early 20s, buy a hype plushie",
    "username": "Hy_Purr_liquid",
    "timestamp": 1735432157000,
    "createdAt": "2024-12-29T00:29:17.000Z",
    "isReply": true,
    "isRetweet": false,
    "likes": 1,
    "retweetCount": 0,
    "replies": 0,
    "photos": [],
    "videos": [],
    "urls": [],
    "permanentUrl": "https://twitter.com/Hy_Purr_liquid/status/1873164352184107149",
    "inReplyToStatusId": "1873084591155888633",
    "hashtags": []
  },
  {
    "id": "1873152113666351341",
    "text": "@HighCoinviction staking about to commence any day now, 16 validators all have staked hype on main net https://t.co/XjIo3eqA1b",
    "username": "Hy_Purr_liquid",
    "timestamp": 1735429240000,
    "createdAt": "2024-12-28T23:40:40.000Z",
    "isReply": true,
    "isRetweet": false,
    "likes": 3,
    "retweetCount": 0,
    "replies": 1,
    "photos": [
      {
        "id": "1873152104011055106",
        "url": "https://pbs.twimg.com/media/Gf7F6gnawAI1Z3w.jpg"
      }
    ],
    "videos": [],
    "urls": [],
    "permanentUrl": "https://twitter.com/Hy_Purr_liquid/status/1873152113666351341",
    "inReplyToStatusId": "1873031189168308261",
    "hashtags": []
  },
  {
    "id": "1872975967049924752",
    "text": "@larryfink_jr That was the 300mill set aside on TGE",
    "username": "Hy_Purr_liquid",
    "timestamp": 1735387243000,
    "createdAt": "2024-12-28T12:00:43.000Z",
    "isReply": true,
    "isRetweet": false,
    "likes": 1,
    "retweetCount": 0,
    "replies": 0,
    "photos": [],
    "videos": [],
    "urls": [],
    "permanentUrl": "https://twitter.com/Hy_Purr_liquid/status/1872975967049924752",
    "inReplyToStatusId": "1872975549045588105",
    "hashtags": []
  },
  {
    "id": "1872975880164917717",
    "text": "@KyleSamani went instablock on @sassal0x after this reply.",
    "username": "Hy_Purr_liquid",
    "timestamp": 1735387222000,
    "createdAt": "2024-12-28T12:00:22.000Z",
    "isReply": false,
    "isRetweet": false,
    "likes": 1,
    "retweetCount": 0,
    "replies": 0,
    "photos": [],
    "videos": [],
    "urls": [],
    "permanentUrl": "https://twitter.com/Hy_Purr_liquid/status/1872975880164917717",
    "quotedStatusId": "1872959616096801247",
    "hashtags": []
  },
  {
    "id": "1872975526278906283",
    "text": "@mk4_lul @KyleSamani  blocked Sassal after this",
    "username": "Hy_Purr_liquid",
    "timestamp": 1735387138000,
    "createdAt": "2024-12-28T11:58:58.000Z",
    "isReply": true,
    "isRetweet": false,
    "likes": 7,
    "retweetCount": 0,
    "replies": 0,
    "photos": [],
    "videos": [],
    "urls": [],
    "permanentUrl": "https://twitter.com/Hy_Purr_liquid/status/1872975526278906283",
    "inReplyToStatusId": "1872959616096801247",
    "hashtags": []
  },
  {
    "id": "1872974555578507347",
    "text": "@jon_charb pretty sure its baked into the L1 that cancels get priority to stop toxic flows. They actually sacrificed a huge amount of volume by doing this",
    "username": "Hy_Purr_liquid",
    "timestamp": 1735386906000,
    "createdAt": "2024-12-28T11:55:06.000Z",
    "isReply": true,
    "isRetweet": false,
    "likes": 0,
    "retweetCount": 0,
    "replies": 0,
    "photos": [],
    "videos": [],
    "urls": [],
    "permanentUrl": "https://twitter.com/Hy_Purr_liquid/status/1872974555578507347",
    "inReplyToStatusId": "1872767475399705080",
    "hashtags": []
  },
  {
    "id": "1872971392804872685",
    "text": "Mainnet validators have got hype staked in them by the looks of it. https://t.co/Yymr2Rze2X",
    "username": "Hy_Purr_liquid",
    "timestamp": 1735386152000,
    "createdAt": "2024-12-28T11:42:32.000Z",
    "isReply": false,
    "isRetweet": false,
    "likes": 75,
    "retweetCount": 6,
    "replies": 3,
    "photos": [
      {
        "id": "1872970944677068800",
        "url": "https://pbs.twimg.com/media/Gf4hJpgawAA_onV.jpg"
      }
    ],
    "videos": [],
    "urls": [],
    "permanentUrl": "https://twitter.com/Hy_Purr_liquid/status/1872971392804872685",
    "hashtags": []
  },
  {
    "id": "1872784675984556261",
    "text": "@KyleSamani @RyanWatkins_ How can HL be a great CEX \nif a terrible DEX \nhas better UX?",
    "username": "Hy_Purr_liquid",
    "timestamp": 1735341636000,
    "createdAt": "2024-12-27T23:20:36.000Z",
    "isReply": true,
    "isRetweet": false,
    "likes": 2,
    "retweetCount": 0,
    "replies": 0,
    "photos": [],
    "videos": [],
    "urls": [],
    "permanentUrl": "https://twitter.com/Hy_Purr_liquid/status/1872784675984556261",
    "inReplyToStatusId": "1872663719324615046",
    "hashtags": []
  },
  {
    "id": "1872783869285679296",
    "text": "@0xOmnia what is OSS",
    "username": "Hy_Purr_liquid",
    "timestamp": 1735341443000,
    "createdAt": "2024-12-27T23:17:23.000Z",
    "isReply": true,
    "isRetweet": false,
    "likes": 0,
    "retweetCount": 0,
    "replies": 1,
    "photos": [],
    "videos": [],
    "urls": [],
    "permanentUrl": "https://twitter.com/Hy_Purr_liquid/status/1872783869285679296",
    "inReplyToStatusId": "1872681005062160579",
    "hashtags": []
  },
  {
    "id": "1872775838904795454",
    "text": "@KyleSamani @RyanWatkins_ Drift is a terrible Dex",
    "username": "Hy_Purr_liquid",
    "timestamp": 1735339529000,
    "createdAt": "2024-12-27T22:45:29.000Z",
    "isReply": true,
    "isRetweet": false,
    "likes": 1,
    "retweetCount": 0,
    "replies": 1,
    "photos": [],
    "videos": [],
    "urls": [],
    "permanentUrl": "https://twitter.com/Hy_Purr_liquid/status/1872775838904795454",
    "inReplyToStatusId": "1872663719324615046",
    "hashtags": []
  },
  {
    "id": "1872773479902413224",
    "text": "@KyleSamani @RyanWatkins_ Drift has better UX",
    "username": "Hy_Purr_liquid",
    "timestamp": 1735338966000,
    "createdAt": "2024-12-27T22:36:06.000Z",
    "isReply": true,
    "isRetweet": false,
    "likes": 0,
    "retweetCount": 0,
    "replies": 0,
    "photos": [],
    "videos": [],
    "urls": [],
    "permanentUrl": "https://twitter.com/Hy_Purr_liquid/status/1872773479902413224",
    "inReplyToStatusId": "1872663719324615046",
    "hashtags": []
  },
  {
    "id": "1872772368642523278",
    "text": "@143gojo people thought it would effect their airdrop\nno way  HL would pull a stunt like that",
    "username": "Hy_Purr_liquid",
    "timestamp": 1735338701000,
    "createdAt": "2024-12-27T22:31:41.000Z",
    "isReply": true,
    "isRetweet": false,
    "likes": 1,
    "retweetCount": 0,
    "replies": 1,
    "photos": [],
    "videos": [],
    "urls": [],
    "permanentUrl": "https://twitter.com/Hy_Purr_liquid/status/1872772368642523278",
    "inReplyToStatusId": "1872545519777763822",
    "hashtags": []
  },
  {
    "id": "1872624867587334622",
    "text": "@onthegamble @TylerDurden yes one just sold 1mill hype for I around 25mill and he still has 1.5mill hype, probably 1000-2000 people got a drop worth more than 1 mill if they held",
    "username": "Hy_Purr_liquid",
    "timestamp": 1735303534000,
    "createdAt": "2024-12-27T12:45:34.000Z",
    "isReply": true,
    "isRetweet": false,
    "likes": 1,
    "retweetCount": 0,
    "replies": 0,
    "photos": [],
    "videos": [],
    "urls": [],
    "permanentUrl": "https://twitter.com/Hy_Purr_liquid/status/1872624867587334622",
    "inReplyToStatusId": "1872512035310944299",
    "hashtags": []
  },
  {
    "id": "1872564549263724573",
    "text": "@kirbyongeo Im not selling, the people in the top 5k who yeeted the airdrop are the most likely to yeet the nft",
    "username": "Hy_Purr_liquid",
    "timestamp": 1735289153000,
    "createdAt": "2024-12-27T08:45:53.000Z",
    "isReply": true,
    "isRetweet": false,
    "likes": 4,
    "retweetCount": 0,
    "replies": 1,
    "photos": [],
    "videos": [],
    "urls": [],
    "permanentUrl": "https://twitter.com/Hy_Purr_liquid/status/1872564549263724573",
    "inReplyToStatusId": "1872564172090917090",
    "hashtags": []
  },
  {
    "id": "1872558522342457662",
    "text": "@kirbyongeo Theres no way Id sell the nft for 30k",
    "username": "Hy_Purr_liquid",
    "timestamp": 1735287716000,
    "createdAt": "2024-12-27T08:21:56.000Z",
    "isReply": true,
    "isRetweet": false,
    "likes": 3,
    "retweetCount": 0,
    "replies": 2,
    "photos": [],
    "videos": [],
    "urls": [],
    "permanentUrl": "https://twitter.com/Hy_Purr_liquid/status/1872558522342457662",
    "inReplyToStatusId": "1872558200937123908",
    "hashtags": []
  },
  {
    "id": "1872555451784855970",
    "text": "@kirbyongeo How can you sell something you haven't even received yet",
    "username": "Hy_Purr_liquid",
    "timestamp": 1735286984000,
    "createdAt": "2024-12-27T08:09:44.000Z",
    "isReply": true,
    "isRetweet": false,
    "likes": 4,
    "retweetCount": 0,
    "replies": 1,
    "photos": [],
    "videos": [],
    "urls": [],
    "permanentUrl": "https://twitter.com/Hy_Purr_liquid/status/1872555451784855970",
    "inReplyToStatusId": "1872537729462112273",
    "hashtags": []
  },
  {
    "id": "1872555095872901153",
    "text": "@vladtenev The team that turned off the buy button pushing for regulation \ngrifter",
    "username": "Hy_Purr_liquid",
    "timestamp": 1735286899000,
    "createdAt": "2024-12-27T08:08:19.000Z",
    "isReply": true,
    "isRetweet": false,
    "likes": 5,
    "retweetCount": 0,
    "replies": 0,
    "photos": [],
    "videos": [],
    "urls": [],
    "permanentUrl": "https://twitter.com/Hy_Purr_liquid/status/1872555095872901153",
    "inReplyToStatusId": "1872456294076215374",
    "hashtags": []
  },
  {
    "id": "1872438873793642981",
    "text": "@Finch_in_flight pretty sure this is the same for every perps platform including Binance",
    "username": "Hy_Purr_liquid",
    "timestamp": 1735259190000,
    "createdAt": "2024-12-27T00:26:30.000Z",
    "isReply": true,
    "isRetweet": false,
    "likes": 3,
    "retweetCount": 0,
    "replies": 0,
    "photos": [],
    "videos": [],
    "urls": [],
    "permanentUrl": "https://twitter.com/Hy_Purr_liquid/status/1872438873793642981",
    "inReplyToStatusId": "1872251888139473153",
    "hashtags": []
  },
  {
    "id": "1872436870543823118",
    "text": "@GYAT_HL https://t.co/2hUhsIaRNp pretty sure this is monitoring mainnet now, the 12 new validators still not validating blocks",
    "username": "Hy_Purr_liquid",
    "timestamp": 1735258712000,
    "createdAt": "2024-12-27T00:18:32.000Z",
    "isReply": true,
    "isRetweet": false,
    "likes": 1,
    "retweetCount": 0,
    "replies": 0,
    "photos": [],
    "videos": [],
    "urls": [
      "https://hypurrscan.io/staking"
    ],
    "permanentUrl": "https://twitter.com/Hy_Purr_liquid/status/1872436870543823118",
    "inReplyToStatusId": "1872436534068363755",
    "hashtags": []
  },
  {
    "id": "1872436497011655000",
    "text": "@vladyoo @stoicsavage For me unless you are on your own hyper performant L1 chain, you simply can't compete against it.",
    "username": "Hy_Purr_liquid",
    "timestamp": 1735258623000,
    "createdAt": "2024-12-27T00:17:03.000Z",
    "isReply": true,
    "isRetweet": false,
    "likes": 2,
    "retweetCount": 0,
    "replies": 1,
    "photos": [],
    "videos": [],
    "urls": [],
    "permanentUrl": "https://twitter.com/Hy_Purr_liquid/status/1872436497011655000",
    "inReplyToStatusId": "1872351838034604419",
    "hashtags": []
  },
  {
    "id": "1872435471600751028",
    "text": "@vladyoo @stoicsavage no",
    "username": "Hy_Purr_liquid",
    "timestamp": 1735258379000,
    "createdAt": "2024-12-27T00:12:59.000Z",
    "isReply": true,
    "isRetweet": false,
    "likes": 0,
    "retweetCount": 0,
    "replies": 0,
    "photos": [],
    "videos": [],
    "urls": [],
    "permanentUrl": "https://twitter.com/Hy_Purr_liquid/status/1872435471600751028",
    "inReplyToStatusId": "1872351838034604419",
    "hashtags": []
  },
  {
    "id": "1872434985153753156",
    "text": "Get the feeling staking is just days away now\n\nhyperliquid the \"cex with a couple of extra steps\" https://t.co/9UnCQJck6Y",
    "username": "Hy_Purr_liquid",
    "timestamp": 1735258263000,
    "createdAt": "2024-12-27T00:11:03.000Z",
    "isReply": false,
    "isRetweet": false,
    "likes": 90,
    "retweetCount": 7,
    "replies": 6,
    "photos": [
      {
        "id": "1872434635394957313",
        "url": "https://pbs.twimg.com/media/Gfw5YVvawAEIAlO.jpg"
      }
    ],
    "videos": [],
    "urls": [],
    "permanentUrl": "https://twitter.com/Hy_Purr_liquid/status/1872434985153753156",
    "hashtags": []
  },
  {
    "id": "1872410526569087169",
    "text": "@belizardd Pendle is literally the only reason I ever use eth now",
    "username": "Hy_Purr_liquid",
    "timestamp": 1735252431000,
    "createdAt": "2024-12-26T22:33:51.000Z",
    "isReply": true,
    "isRetweet": false,
    "likes": 2,
    "retweetCount": 0,
    "replies": 0,
    "photos": [],
    "videos": [],
    "urls": [],
    "permanentUrl": "https://twitter.com/Hy_Purr_liquid/status/1872410526569087169",
    "inReplyToStatusId": "1871859152336957856",
    "hashtags": []
  },
  {
    "id": "1872409895305465982",
    "text": "@SaulHedge @crypto_adair Could have made a $100 spot trade and held it for a few points",
    "username": "Hy_Purr_liquid",
    "timestamp": 1735252281000,
    "createdAt": "2024-12-26T22:31:21.000Z",
    "isReply": true,
    "isRetweet": false,
    "likes": 2,
    "retweetCount": 0,
    "replies": 0,
    "photos": [],
    "videos": [],
    "urls": [],
    "permanentUrl": "https://twitter.com/Hy_Purr_liquid/status/1872409895305465982",
    "inReplyToStatusId": "1872305030700978441",
    "hashtags": []
  },
  {
    "id": "1872395003240325229",
    "text": "@Fourb_HL He still has 1.5 mill hype its not like he sold his entire stack \nnet positive those coins sold now have an acquisition price of $25+",
    "username": "Hy_Purr_liquid",
    "timestamp": 1735248730000,
    "createdAt": "2024-12-26T21:32:10.000Z",
    "isReply": true,
    "isRetweet": false,
    "likes": 6,
    "retweetCount": 0,
    "replies": 1,
    "photos": [],
    "videos": [],
    "urls": [],
    "permanentUrl": "https://twitter.com/Hy_Purr_liquid/status/1872395003240325229",
    "inReplyToStatusId": "1872273099120599051",
    "hashtags": []
  },
  {
    "id": "1872275539001786714",
    "text": "@Degenomist_ No its already happened",
    "username": "Hy_Purr_liquid",
    "timestamp": 1735220248000,
    "createdAt": "2024-12-26T13:37:28.000Z",
    "isReply": true,
    "isRetweet": false,
    "likes": 6,
    "retweetCount": 0,
    "replies": 2,
    "photos": [],
    "videos": [],
    "urls": [],
    "permanentUrl": "https://twitter.com/Hy_Purr_liquid/status/1872275539001786714",
    "inReplyToStatusId": "1872090261092008021",
    "hashtags": []
  },
  {
    "id": "1872052915281789231",
    "text": "@markjeffrey Validator set will be expanded to 16 within the next 30 days. \nTook a different route to decentralising - disruptors do things differently.",
    "username": "Hy_Purr_liquid",
    "timestamp": 1735167170000,
    "createdAt": "2024-12-25T22:52:50.000Z",
    "isReply": true,
    "isRetweet": false,
    "likes": 1,
    "retweetCount": 0,
    "replies": 0,
    "photos": [],
    "videos": [],
    "urls": [],
    "permanentUrl": "https://twitter.com/Hy_Purr_liquid/status/1872052915281789231",
    "inReplyToStatusId": "1865573572372201783",
    "hashtags": []
  },
  {
    "id": "1872050501522804836",
    "text": "@Cryptilt @rasmr_eth stage 1 build oncahin perps and spot thats as good or better than CEX\nstage 2 decentralise the validator set (likely within 30 days)\nDisruptors use a different playbook https://t.co/9YDkoMGyKu",
    "username": "Hy_Purr_liquid",
    "timestamp": 1735166595000,
    "createdAt": "2024-12-25T22:43:15.000Z",
    "isReply": true,
    "isRetweet": false,
    "likes": 2,
    "retweetCount": 0,
    "replies": 0,
    "photos": [
      {
        "id": "1872050494006599680",
        "url": "https://pbs.twimg.com/media/GfrcAXjboAAJ5qk.png"
      }
    ],
    "videos": [],
    "urls": [],
    "permanentUrl": "https://twitter.com/Hy_Purr_liquid/status/1872050501522804836",
    "inReplyToStatusId": "1871779655289889233",
    "hashtags": []
  },
  {
    "id": "1872047761849467153",
    "text": "@ThinkingUSD Technically we can blame Hyperliquid team for FTX demise, if Jeff's trading firm did trade there, Alameda would have front run or copied all their trades and it would have been extremely profitable. Sadly they chose not to trade there because of too many red flags",
    "username": "Hy_Purr_liquid",
    "timestamp": 1735165942000,
    "createdAt": "2024-12-25T22:32:22.000Z",
    "isReply": true,
    "isRetweet": false,
    "likes": 5,
    "retweetCount": 0,
    "replies": 1,
    "photos": [],
    "videos": [],
    "urls": [],
    "permanentUrl": "https://twitter.com/Hy_Purr_liquid/status/1872047761849467153",
    "inReplyToStatusId": "1872031675414360119",
    "hashtags": []
  },
  {
    "id": "1871908498789069263",
    "text": "@llamaonthebrink @farcaster_xyz Make it less boring",
    "username": "Hy_Purr_liquid",
    "timestamp": 1735132739000,
    "createdAt": "2024-12-25T13:18:59.000Z",
    "isReply": true,
    "isRetweet": false,
    "likes": 0,
    "retweetCount": 0,
    "replies": 0,
    "photos": [],
    "videos": [],
    "urls": [],
    "permanentUrl": "https://twitter.com/Hy_Purr_liquid/status/1871908498789069263",
    "inReplyToStatusId": "1871621654075572629",
    "hashtags": []
  },
  {
    "id": "1871892651974537541",
    "text": "@Hycene2Hycene followed the wallets TXs\nThe main wallet transferred funds to this wallet https://t.co/T3ODQ5q6Qw which then does small transfers to another wallet that sells it",
    "username": "Hy_Purr_liquid",
    "timestamp": 1735128960000,
    "createdAt": "2024-12-25T12:16:00.000Z",
    "isReply": true,
    "isRetweet": false,
    "likes": 11,
    "retweetCount": 0,
    "replies": 0,
    "photos": [],
    "videos": [],
    "urls": [
      "https://hypurrscan.io/address/0x396fe28c95bf3252178800774ccd76bb26309373"
    ],
    "permanentUrl": "https://twitter.com/Hy_Purr_liquid/status/1871892651974537541",
    "inReplyToStatusId": "1871845270071501027",
    "hashtags": []
  },
  {
    "id": "1871853797561217097",
    "text": "@cryptofordummi5 1m hype",
    "username": "Hy_Purr_liquid",
    "timestamp": 1735119697000,
    "createdAt": "2024-12-25T09:41:37.000Z",
    "isReply": true,
    "isRetweet": false,
    "likes": 7,
    "retweetCount": 0,
    "replies": 0,
    "photos": [],
    "videos": [],
    "urls": [],
    "permanentUrl": "https://twitter.com/Hy_Purr_liquid/status/1871853797561217097",
    "inReplyToStatusId": "1871853024563654703",
    "hashtags": []
  },
  {
    "id": "1871841661028106680",
    "text": "The 1 million sell wallet is down to 490k hype and has started twapping another 200k at a rate of about 150 per minute which would take it 24 hours to complete",
    "username": "Hy_Purr_liquid",
    "timestamp": 1735116803000,
    "createdAt": "2024-12-25T08:53:23.000Z",
    "isReply": false,
    "isRetweet": false,
    "likes": 184,
    "retweetCount": 9,
    "replies": 14,
    "photos": [],
    "videos": [],
    "urls": [],
    "permanentUrl": "https://twitter.com/Hy_Purr_liquid/status/1871841661028106680",
    "hashtags": []
  },
  {
    "id": "1871777357541027862",
    "text": "@bluegwei @ThorHartvigsen they will inflate the circulating supply is what I meant\nWith burn the supply is less than 1 billion already",
    "username": "Hy_Purr_liquid",
    "timestamp": 1735101472000,
    "createdAt": "2024-12-25T04:37:52.000Z",
    "isReply": true,
    "isRetweet": false,
    "likes": 1,
    "retweetCount": 0,
    "replies": 1,
    "photos": [],
    "videos": [],
    "urls": [],
    "permanentUrl": "https://twitter.com/Hy_Purr_liquid/status/1871777357541027862",
    "inReplyToStatusId": "1871776274852749631",
    "hashtags": []
  },
  {
    "id": "1871775952470167829",
    "text": "Hype over $30 even with a 350k twap being executed over the past 18 hours. There is still 500k hype likely to be sold from the wallet ~ $15 million but with hype doing $400mill a day it should have minimal impact the way they are going about it",
    "username": "Hy_Purr_liquid",
    "timestamp": 1735101137000,
    "createdAt": "2024-12-25T04:32:17.000Z",
    "isReply": false,
    "isRetweet": false,
    "likes": 54,
    "retweetCount": 2,
    "replies": 3,
    "photos": [],
    "videos": [],
    "urls": [],
    "permanentUrl": "https://twitter.com/Hy_Purr_liquid/status/1871775952470167829",
    "hashtags": []
  },
  {
    "id": "1871770187982315854",
    "text": "@mr_saaaaaaaj @0xSisyphus doesnt exactly make it Luna - they are working on an EVM app and have nothing to do with the L1 team",
    "username": "Hy_Purr_liquid",
    "timestamp": 1735099763000,
    "createdAt": "2024-12-25T04:09:23.000Z",
    "isReply": true,
    "isRetweet": false,
    "likes": 1,
    "retweetCount": 0,
    "replies": 0,
    "photos": [],
    "videos": [],
    "urls": [],
    "permanentUrl": "https://twitter.com/Hy_Purr_liquid/status/1871770187982315854",
    "inReplyToStatusId": "1871593226483958093",
    "hashtags": []
  },
  {
    "id": "1871769700939817037",
    "text": "@blknoiz06 Has Raoul stopped shilling it, must have dumped his bag on one of the unlocks if he has",
    "username": "Hy_Purr_liquid",
    "timestamp": 1735099647000,
    "createdAt": "2024-12-25T04:07:27.000Z",
    "isReply": true,
    "isRetweet": false,
    "likes": 0,
    "retweetCount": 0,
    "replies": 0,
    "photos": [],
    "videos": [],
    "urls": [],
    "permanentUrl": "https://twitter.com/Hy_Purr_liquid/status/1871769700939817037",
    "inReplyToStatusId": "1871659787794215134",
    "hashtags": []
  },
  {
    "id": "1871762967894839738",
    "text": "@cprkrn @sershokunin You are purchasing the coin from another user who has plaed a bid or from hyperliquidity",
    "username": "Hy_Purr_liquid",
    "timestamp": 1735098041000,
    "createdAt": "2024-12-25T03:40:41.000Z",
    "isReply": true,
    "isRetweet": false,
    "likes": 0,
    "retweetCount": 0,
    "replies": 0,
    "photos": [],
    "videos": [],
    "urls": [],
    "permanentUrl": "https://twitter.com/Hy_Purr_liquid/status/1871762967894839738",
    "inReplyToStatusId": "1871709739035566098",
    "hashtags": []
  },
  {
    "id": "1871762265441181801",
    "text": "@jai_prasad17 what is it?",
    "username": "Hy_Purr_liquid",
    "timestamp": 1735097874000,
    "createdAt": "2024-12-25T03:37:54.000Z",
    "isReply": true,
    "isRetweet": false,
    "likes": 0,
    "retweetCount": 0,
    "replies": 0,
    "photos": [],
    "videos": [],
    "urls": [],
    "permanentUrl": "https://twitter.com/Hy_Purr_liquid/status/1871762265441181801",
    "inReplyToStatusId": "1871719310391201902",
    "hashtags": []
  },
  {
    "id": "1871733240337469881",
    "text": "@CryptoGuyjin @stoicsavage @CL207 Hackers appreciate good ux and deep liquidity",
    "username": "Hy_Purr_liquid",
    "timestamp": 1735090954000,
    "createdAt": "2024-12-25T01:42:34.000Z",
    "isReply": true,
    "isRetweet": false,
    "likes": 1,
    "retweetCount": 0,
    "replies": 1,
    "photos": [],
    "videos": [],
    "urls": [],
    "permanentUrl": "https://twitter.com/Hy_Purr_liquid/status/1871733240337469881",
    "inReplyToStatusId": "1871455573751091513",
    "hashtags": []
  },
  {
    "id": "1871729602462470420",
    "text": "@0xShual Fud was net positive\nGot masses talking about hl and team will no doubt double down on security",
    "username": "Hy_Purr_liquid",
    "timestamp": 1735090086000,
    "createdAt": "2024-12-25T01:28:06.000Z",
    "isReply": true,
    "isRetweet": false,
    "likes": 4,
    "retweetCount": 0,
    "replies": 0,
    "photos": [],
    "videos": [],
    "urls": [],
    "permanentUrl": "https://twitter.com/Hy_Purr_liquid/status/1871729602462470420",
    "inReplyToStatusId": "1871565327257276883",
    "hashtags": []
  },
  {
    "id": "1871728922104316071",
    "text": "@reisnertobias Dont think so",
    "username": "Hy_Purr_liquid",
    "timestamp": 1735089924000,
    "createdAt": "2024-12-25T01:25:24.000Z",
    "isReply": true,
    "isRetweet": false,
    "likes": 1,
    "retweetCount": 0,
    "replies": 0,
    "photos": [],
    "videos": [],
    "urls": [],
    "permanentUrl": "https://twitter.com/Hy_Purr_liquid/status/1871728922104316071",
    "inReplyToStatusId": "1871622231924908083",
    "hashtags": []
  },
  {
    "id": "1871728858506096703",
    "text": "@jimihendrixgin @pvp_dot_trade @Hypurrfun A hyperliquid spot shitcoin index fund",
    "username": "Hy_Purr_liquid",
    "timestamp": 1735089909000,
    "createdAt": "2024-12-25T01:25:09.000Z",
    "isReply": true,
    "isRetweet": false,
    "likes": 3,
    "retweetCount": 0,
    "replies": 1,
    "photos": [],
    "videos": [],
    "urls": [],
    "permanentUrl": "https://twitter.com/Hy_Purr_liquid/status/1871728858506096703",
    "inReplyToStatusId": "1871301760415068556",
    "hashtags": []
  },
  {
    "id": "1871728381026607211",
    "text": "This is bang on",
    "username": "Hy_Purr_liquid",
    "timestamp": 1735089795000,
    "createdAt": "2024-12-25T01:23:15.000Z",
    "isReply": false,
    "isRetweet": false,
    "likes": 4,
    "retweetCount": 0,
    "replies": 0,
    "photos": [],
    "videos": [],
    "urls": [],
    "permanentUrl": "https://twitter.com/Hy_Purr_liquid/status/1871728381026607211",
    "quotedStatusId": "1871544517440250003",
    "hashtags": []
  },
  {
    "id": "1871693455229161835",
    "text": "In the end FUD is net positive, it shows you're project has gained a huge amount of attention and in this case demonstrates how big Hyperliquid has become, at one stage they had nearly 70% of all arbitrum USDC (2.4billion) in its bridge which obviously is a huge target.…",
    "username": "Hy_Purr_liquid",
    "timestamp": 1735081468000,
    "createdAt": "2024-12-24T23:04:28.000Z",
    "isReply": false,
    "isRetweet": false,
    "likes": 65,
    "retweetCount": 4,
    "replies": 4,
    "photos": [],
    "videos": [],
    "urls": [],
    "permanentUrl": "https://twitter.com/Hy_Purr_liquid/status/1871693455229161835",
    "quotedStatusId": "1871202572587118629",
    "hashtags": []
  },
  {
    "id": "1871689594091233739",
    "text": "@KyleSamani @kunalgoel Please don't compare dogshit to truffles",
    "username": "Hy_Purr_liquid",
    "timestamp": 1735080548000,
    "createdAt": "2024-12-24T22:49:08.000Z",
    "isReply": true,
    "isRetweet": false,
    "likes": 10,
    "retweetCount": 0,
    "replies": 0,
    "photos": [],
    "videos": [],
    "urls": [],
    "permanentUrl": "https://twitter.com/Hy_Purr_liquid/status/1871689594091233739",
    "inReplyToStatusId": "1871687767400546625",
    "hashtags": []
  },
  {
    "id": "1871688871521763499",
    "text": "@ThorHartvigsen 100k hype has also been burned on top of this, so around 1million hype a year will get burned + EVM will require hype for TXs. I would expect there to be staking emissions soon, which will add a bit of inflation",
    "username": "Hy_Purr_liquid",
    "timestamp": 1735080375000,
    "createdAt": "2024-12-24T22:46:15.000Z",
    "isReply": true,
    "isRetweet": false,
    "likes": 6,
    "retweetCount": 1,
    "replies": 2,
    "photos": [],
    "videos": [],
    "urls": [],
    "permanentUrl": "https://twitter.com/Hy_Purr_liquid/status/1871688871521763499",
    "inReplyToStatusId": "1871547008303222920",
    "hashtags": []
  },
  {
    "id": "1870980422504779967",
    "text": "@YippieDeGod @HyperliquidX @laurentzeimes Do you have the address?",
    "username": "Hy_Purr_liquid",
    "timestamp": 1734911468000,
    "createdAt": "2024-12-22T23:51:08.000Z",
    "isReply": true,
    "isRetweet": false,
    "likes": 0,
    "retweetCount": 0,
    "replies": 2,
    "photos": [],
    "videos": [],
    "urls": [],
    "permanentUrl": "https://twitter.com/Hy_Purr_liquid/status/1870980422504779967",
    "inReplyToStatusId": "1870961998005215712",
    "hashtags": []
  },
  {
    "id": "1870962971230503257",
    "text": "@greenytrades Hyperliquid airdrop nft",
    "username": "Hy_Purr_liquid",
    "timestamp": 1734907307000,
    "createdAt": "2024-12-22T22:41:47.000Z",
    "isReply": true,
    "isRetweet": false,
    "likes": 0,
    "retweetCount": 0,
    "replies": 0,
    "photos": [],
    "videos": [],
    "urls": [],
    "permanentUrl": "https://twitter.com/Hy_Purr_liquid/status/1870962971230503257",
    "inReplyToStatusId": "1870473105334018163",
    "hashtags": []
  },
  {
    "id": "1870961693234483688",
    "text": "@KevinWSHPod @HyperliquidX yep gud podcast  \nand people should know by now\nHyperliquid never leaks alpha",
    "username": "Hy_Purr_liquid",
    "timestamp": 1734907003000,
    "createdAt": "2024-12-22T22:36:43.000Z",
    "isReply": true,
    "isRetweet": false,
    "likes": 3,
    "retweetCount": 0,
    "replies": 1,
    "photos": [],
    "videos": [],
    "urls": [],
    "permanentUrl": "https://twitter.com/Hy_Purr_liquid/status/1870961693234483688",
    "inReplyToStatusId": "1870711060602429593",
    "hashtags": []
  },
  {
    "id": "1870945549974905211",
    "text": "@Squishy_Chris_D @0xOmnia People are offering to buy test net hype coins to improve their testnet validator standing so they can become  a main net validator",
    "username": "Hy_Purr_liquid",
    "timestamp": 1734903154000,
    "createdAt": "2024-12-22T21:32:34.000Z",
    "isReply": true,
    "isRetweet": false,
    "likes": 2,
    "retweetCount": 0,
    "replies": 1,
    "photos": [],
    "videos": [],
    "urls": [],
    "permanentUrl": "https://twitter.com/Hy_Purr_liquid/status/1870945549974905211",
    "inReplyToStatusId": "1870933908659089733",
    "hashtags": []
  },
  {
    "id": "1870761617769828697",
    "text": "@bottommaker_ it went from $40million to $380million in 3 weeks and you think they should have stayed in stables?\nNGMI",
    "username": "Hy_Purr_liquid",
    "timestamp": 1734859301000,
    "createdAt": "2024-12-22T09:21:41.000Z",
    "isReply": true,
    "isRetweet": false,
    "likes": 0,
    "retweetCount": 0,
    "replies": 0,
    "photos": [],
    "videos": [],
    "urls": [],
    "permanentUrl": "https://twitter.com/Hy_Purr_liquid/status/1870761617769828697",
    "inReplyToStatusId": "1870436293756534852",
    "hashtags": []
  },
  {
    "id": "1870761357248979385",
    "text": "@Cryptotrissy @kelxyz_ study L1s that do 200tps\nstudy teams with quant trading backgrounds\nstudy self funded teams that give the middle finger to VCs\nstudy teams who are too busy building to larp on social media\nRetardio",
    "username": "Hy_Purr_liquid",
    "timestamp": 1734859239000,
    "createdAt": "2024-12-22T09:20:39.000Z",
    "isReply": true,
    "isRetweet": false,
    "likes": 2,
    "retweetCount": 0,
    "replies": 0,
    "photos": [],
    "videos": [],
    "urls": [],
    "permanentUrl": "https://twitter.com/Hy_Purr_liquid/status/1870761357248979385",
    "inReplyToStatusId": "1870680377511333977",
    "hashtags": []
  },
  {
    "id": "1870760700941095121",
    "text": "@CapitalMonet staking just around the corner, TGE holders will be able to live off the staking rewards",
    "username": "Hy_Purr_liquid",
    "timestamp": 1734859082000,
    "createdAt": "2024-12-22T09:18:02.000Z",
    "isReply": true,
    "isRetweet": false,
    "likes": 6,
    "retweetCount": 0,
    "replies": 1,
    "photos": [],
    "videos": [],
    "urls": [],
    "permanentUrl": "https://twitter.com/Hy_Purr_liquid/status/1870760700941095121",
    "inReplyToStatusId": "1870725334985048445",
    "hashtags": []
  },
  {
    "id": "1870759575093436662",
    "text": "The Hyperliquid treasury is now worth $380million dollars. Loading up on $hype straight after TGE has been another chad move by the team. \nWill they diversify in the future, hold a bit of stablecoin, I think everyone is pretty happy with the perpetual buyback machine.",
    "username": "Hy_Purr_liquid",
    "timestamp": 1734858814000,
    "createdAt": "2024-12-22T09:13:34.000Z",
    "isReply": false,
    "isRetweet": false,
    "likes": 30,
    "retweetCount": 3,
    "replies": 5,
    "photos": [],
    "videos": [],
    "urls": [],
    "permanentUrl": "https://twitter.com/Hy_Purr_liquid/status/1870759575093436662",
    "quotedStatusId": "1870265945933128028",
    "hashtags": []
  },
  {
    "id": "1870758160052760982",
    "text": "@CryptoGuyjin yeah I also thought they should diversify a bit, HLP would be perfect\nhaving said that, they turned 40million into $380million in 3.5 weeks, first few weeks is the optimal time to load up on hype, team clearly knew this",
    "username": "Hy_Purr_liquid",
    "timestamp": 1734858477000,
    "createdAt": "2024-12-22T09:07:57.000Z",
    "isReply": true,
    "isRetweet": false,
    "likes": 1,
    "retweetCount": 0,
    "replies": 1,
    "photos": [],
    "videos": [],
    "urls": [],
    "permanentUrl": "https://twitter.com/Hy_Purr_liquid/status/1870758160052760982",
    "inReplyToStatusId": "1870744413426819494",
    "hashtags": []
  },
  {
    "id": "1870656202654507374",
    "text": "I forgot \nBTC, ETH / erc20 and Solana bridges \nNative USDC\nEthena deployment\nNative stablecoin deployments",
    "username": "Hy_Purr_liquid",
    "timestamp": 1734834168000,
    "createdAt": "2024-12-22T02:22:48.000Z",
    "isReply": true,
    "isRetweet": false,
    "likes": 6,
    "retweetCount": 0,
    "replies": 0,
    "photos": [],
    "videos": [],
    "urls": [],
    "permanentUrl": "https://twitter.com/Hy_Purr_liquid/status/1870656202654507374",
    "inReplyToStatusId": "1870654746425765901",
    "hashtags": []
  },
  {
    "id": "1870654746425765901",
    "text": "Hyperliquid Burn and buyback on fire and we are still in the first innings.\n\nStill to come \n\nHype Staking and liquid staking\nHYPE spot pairs. \nHYPE collateral for margin. \nHYPE for gas fees on EVM.  \nHYPE,  HLP and perps positions lending\nHYPE listings on all tier 1 CEXs…",
    "username": "Hy_Purr_liquid",
    "timestamp": 1734833821000,
    "createdAt": "2024-12-22T02:17:01.000Z",
    "isReply": false,
    "isRetweet": false,
    "likes": 75,
    "retweetCount": 12,
    "replies": 2,
    "photos": [],
    "videos": [],
    "urls": [],
    "permanentUrl": "https://twitter.com/Hy_Purr_liquid/status/1870654746425765901",
    "quotedStatusId": "1870523254823407946",
    "hashtags": []
  },
  {
    "id": "1870649979926466998",
    "text": "@CC2Ventures I just farmed 1, made generational wealth and avoided all possibilites of accidentally getting my wallet drained and saved myself a shitload of wasted time chasing vapourware",
    "username": "Hy_Purr_liquid",
    "timestamp": 1734832684000,
    "createdAt": "2024-12-22T01:58:04.000Z",
    "isReply": true,
    "isRetweet": false,
    "likes": 4,
    "retweetCount": 0,
    "replies": 1,
    "photos": [],
    "videos": [],
    "urls": [],
    "permanentUrl": "https://twitter.com/Hy_Purr_liquid/status/1870649979926466998",
    "inReplyToStatusId": "1870582503528157312",
    "hashtags": []
  },
  {
    "id": "1870611411153695051",
    "text": "@CapitalMonet still under calculating by over 1billion\nthis is why I havent used it in years\n@coingecko is magnitudes better",
    "username": "Hy_Purr_liquid",
    "timestamp": 1734823489000,
    "createdAt": "2024-12-21T23:24:49.000Z",
    "isReply": true,
    "isRetweet": false,
    "likes": 1,
    "retweetCount": 0,
    "replies": 1,
    "photos": [],
    "videos": [],
    "urls": [],
    "permanentUrl": "https://twitter.com/Hy_Purr_liquid/status/1870611411153695051",
    "inReplyToStatusId": "1870028201860473211",
    "hashtags": []
  },
  {
    "id": "1870583858615480383",
    "text": "@0xWittgenstein “Drift has better ux”",
    "username": "Hy_Purr_liquid",
    "timestamp": 1734816920000,
    "createdAt": "2024-12-21T21:35:20.000Z",
    "isReply": true,
    "isRetweet": false,
    "likes": 1,
    "retweetCount": 0,
    "replies": 0,
    "photos": [],
    "videos": [],
    "urls": [],
    "permanentUrl": "https://twitter.com/Hy_Purr_liquid/status/1870583858615480383",
    "inReplyToStatusId": "1870577019245019520",
    "hashtags": []
  },
  {
    "id": "1870387248077959284",
    "text": "@Vivek4real_ Could pay it off way faster with $ hype",
    "username": "Hy_Purr_liquid",
    "timestamp": 1734770044000,
    "createdAt": "2024-12-21T08:34:04.000Z",
    "isReply": true,
    "isRetweet": false,
    "likes": 4,
    "retweetCount": 0,
    "replies": 0,
    "photos": [],
    "videos": [],
    "urls": [],
    "permanentUrl": "https://twitter.com/Hy_Purr_liquid/status/1870387248077959284",
    "inReplyToStatusId": "1870230965173293460",
    "hashtags": []
  },
  {
    "id": "1870385436419653970",
    "text": "@BussyFiller69 One of many goated moves by the team actually creates a level of excitement over who wins the next bid plus its another fee cash cow",
    "username": "Hy_Purr_liquid",
    "timestamp": 1734769612000,
    "createdAt": "2024-12-21T08:26:52.000Z",
    "isReply": true,
    "isRetweet": false,
    "likes": 3,
    "retweetCount": 0,
    "replies": 0,
    "photos": [],
    "videos": [],
    "urls": [],
    "permanentUrl": "https://twitter.com/Hy_Purr_liquid/status/1870385436419653970",
    "inReplyToStatusId": "1870148169662898526",
    "hashtags": []
  },
  {
    "id": "1870384509671322009",
    "text": "@Sakrexer They have 350million tokens set aside a large portion of these would be intended for staking.",
    "username": "Hy_Purr_liquid",
    "timestamp": 1734769391000,
    "createdAt": "2024-12-21T08:23:11.000Z",
    "isReply": true,
    "isRetweet": false,
    "likes": 6,
    "retweetCount": 0,
    "replies": 0,
    "photos": [],
    "videos": [],
    "urls": [],
    "permanentUrl": "https://twitter.com/Hy_Purr_liquid/status/1870384509671322009",
    "inReplyToStatusId": "1870360396587999526",
    "hashtags": []
  },
  {
    "id": "1870384023559938277",
    "text": "@stevenyuntcap Crypto banter saying he will short it when it was $23 because it was over valued rofl",
    "username": "Hy_Purr_liquid",
    "timestamp": 1734769275000,
    "createdAt": "2024-12-21T08:21:15.000Z",
    "isReply": true,
    "isRetweet": false,
    "likes": 5,
    "retweetCount": 0,
    "replies": 0,
    "photos": [],
    "videos": [],
    "urls": [],
    "permanentUrl": "https://twitter.com/Hy_Purr_liquid/status/1870384023559938277",
    "inReplyToStatusId": "1870339783177990402",
    "hashtags": []
  },
  {
    "id": "1870383422964961520",
    "text": ")How Hyperliquid Flips Base and Solana DeFi combined in 2025\nKey takeaways from my latest hype report\n\nChad team keeps shipping at break neck speed and giving all the spoils to users. Jeff has made crypto great again.",
    "username": "Hy_Purr_liquid",
    "timestamp": 1734769132000,
    "createdAt": "2024-12-21T08:18:52.000Z",
    "isReply": false,
    "isRetweet": false,
    "likes": 17,
    "retweetCount": 3,
    "replies": 1,
    "photos": [],
    "videos": [],
    "urls": [],
    "permanentUrl": "https://twitter.com/Hy_Purr_liquid/status/1870383422964961520",
    "quotedStatusId": "1870145682608165054",
    "hashtags": []
  },
  {
    "id": "1870324219189584166",
    "text": "everyone talks about the eth/btc chart  \n\nno one talks about the hype/sol chart",
    "username": "Hy_Purr_liquid",
    "timestamp": 1734755017000,
    "createdAt": "2024-12-21T04:23:37.000Z",
    "isReply": false,
    "isRetweet": false,
    "likes": 14,
    "retweetCount": 1,
    "replies": 1,
    "photos": [],
    "videos": [],
    "urls": [],
    "permanentUrl": "https://twitter.com/Hy_Purr_liquid/status/1870324219189584166",
    "quotedStatusId": "1870274512736137230",
    "hashtags": []
  },
  {
    "id": "1870323687997788500",
    "text": "@beaniemaxi will all be porting to Hyperliquid soon",
    "username": "Hy_Purr_liquid",
    "timestamp": 1734754890000,
    "createdAt": "2024-12-21T04:21:30.000Z",
    "isReply": true,
    "isRetweet": false,
    "likes": 5,
    "retweetCount": 0,
    "replies": 1,
    "photos": [],
    "videos": [],
    "urls": [],
    "permanentUrl": "https://twitter.com/Hy_Purr_liquid/status/1870323687997788500",
    "inReplyToStatusId": "1870304206441029703",
    "hashtags": []
  },
  {
    "id": "1870322757264970189",
    "text": "@Buhlaque the infinite twap is amazing, this is what you can do when you don't have to listen to VCs",
    "username": "Hy_Purr_liquid",
    "timestamp": 1734754668000,
    "createdAt": "2024-12-21T04:17:48.000Z",
    "isReply": true,
    "isRetweet": false,
    "likes": 2,
    "retweetCount": 0,
    "replies": 0,
    "photos": [],
    "videos": [],
    "urls": [],
    "permanentUrl": "https://twitter.com/Hy_Purr_liquid/status/1870322757264970189",
    "inReplyToStatusId": "1870314180655386782",
    "hashtags": []
  },
  {
    "id": "1870314099172876788",
    "text": "If you hold $sol instead of $hype for the next 12 months\nyou'll know what its like being an eth holder",
    "username": "Hy_Purr_liquid",
    "timestamp": 1734752604000,
    "createdAt": "2024-12-21T03:43:24.000Z",
    "isReply": false,
    "isRetweet": false,
    "likes": 403,
    "retweetCount": 31,
    "replies": 28,
    "photos": [],
    "videos": [],
    "urls": [],
    "permanentUrl": "https://twitter.com/Hy_Purr_liquid/status/1870314099172876788",
    "hashtags": []
  },
  {
    "id": "1870310465165000936",
    "text": "Tier 2 CEXs rushing to list Hyperliquid, doubled overnight, wouldn't recommend trading on any of them https://t.co/mesI9ICbyo",
    "username": "Hy_Purr_liquid",
    "timestamp": 1734751738000,
    "createdAt": "2024-12-21T03:28:58.000Z",
    "isReply": false,
    "isRetweet": false,
    "likes": 81,
    "retweetCount": 5,
    "replies": 5,
    "photos": [
      {
        "id": "1870309947537534976",
        "url": "https://pbs.twimg.com/media/GfSs_OrasAA5dxT.jpg"
      }
    ],
    "videos": [],
    "urls": [],
    "permanentUrl": "https://twitter.com/Hy_Purr_liquid/status/1870310465165000936",
    "hashtags": []
  },
  {
    "id": "1870303018803179666",
    "text": "@pondermint @AlwaysHugo3 i think staking can start before EVM, its on the L1\nliquid staking will need evm",
    "username": "Hy_Purr_liquid",
    "timestamp": 1734749962000,
    "createdAt": "2024-12-21T02:59:22.000Z",
    "isReply": true,
    "isRetweet": false,
    "likes": 2,
    "retweetCount": 0,
    "replies": 1,
    "photos": [],
    "videos": [],
    "urls": [],
    "permanentUrl": "https://twitter.com/Hy_Purr_liquid/status/1870303018803179666",
    "inReplyToStatusId": "1870277536141455387",
    "hashtags": []
  },
  {
    "id": "1870302709208994106",
    "text": "@CapitalMonet ETH 10.5K has this guy been smoking crack",
    "username": "Hy_Purr_liquid",
    "timestamp": 1734749889000,
    "createdAt": "2024-12-21T02:58:09.000Z",
    "isReply": true,
    "isRetweet": false,
    "likes": 2,
    "retweetCount": 0,
    "replies": 0,
    "photos": [],
    "videos": [],
    "urls": [],
    "permanentUrl": "https://twitter.com/Hy_Purr_liquid/status/1870302709208994106",
    "inReplyToStatusId": "1870231608357257616",
    "hashtags": []
  },
  {
    "id": "1870301873544278328",
    "text": "If testnet staking is a guide, you can expect 5-10% staking rewards for your $hype. Looks like the more blocks validated the better the return, \nImagine 10% passive income on your hype https://t.co/psZML9WonH",
    "username": "Hy_Purr_liquid",
    "timestamp": 1734749689000,
    "createdAt": "2024-12-21T02:54:49.000Z",
    "isReply": false,
    "isRetweet": false,
    "likes": 131,
    "retweetCount": 6,
    "replies": 6,
    "photos": [
      {
        "id": "1870301409557860352",
        "url": "https://pbs.twimg.com/media/GfSlOQOb0AAo2DB.png"
      }
    ],
    "videos": [],
    "urls": [],
    "permanentUrl": "https://twitter.com/Hy_Purr_liquid/status/1870301873544278328",
    "hashtags": []
  },
  {
    "id": "1870300164491227175",
    "text": "@ZacharyBrubake4 may as well prepare to be a front end for it and start using the builder codes",
    "username": "Hy_Purr_liquid",
    "timestamp": 1734749282000,
    "createdAt": "2024-12-21T02:48:02.000Z",
    "isReply": true,
    "isRetweet": false,
    "likes": 6,
    "retweetCount": 0,
    "replies": 1,
    "photos": [],
    "videos": [],
    "urls": [],
    "permanentUrl": "https://twitter.com/Hy_Purr_liquid/status/1870300164491227175",
    "inReplyToStatusId": "1870299106465198181",
    "hashtags": []
  },
  {
    "id": "1870299988867330359",
    "text": "@Cryptina_Queen1 hyperliquid doesnt pay for any endorsements, KOLs are toxic, and you must be a bot to be saying its my project",
    "username": "Hy_Purr_liquid",
    "timestamp": 1734749240000,
    "createdAt": "2024-12-21T02:47:20.000Z",
    "isReply": true,
    "isRetweet": false,
    "likes": 2,
    "retweetCount": 0,
    "replies": 1,
    "photos": [],
    "videos": [],
    "urls": [],
    "permanentUrl": "https://twitter.com/Hy_Purr_liquid/status/1870299988867330359",
    "inReplyToStatusId": "1870299259343646834",
    "hashtags": []
  },
  {
    "id": "1870298558425170270",
    "text": "Bybit $144million 24 hour volume hype perps\nBinance will want a piece of the action real soon https://t.co/cXYbcf9lVf",
    "username": "Hy_Purr_liquid",
    "timestamp": 1734748899000,
    "createdAt": "2024-12-21T02:41:39.000Z",
    "isReply": false,
    "isRetweet": false,
    "likes": 125,
    "retweetCount": 14,
    "replies": 4,
    "photos": [
      {
        "id": "1870298313008001026",
        "url": "https://pbs.twimg.com/media/GfSiaArasAItX5J.jpg"
      }
    ],
    "videos": [],
    "urls": [],
    "permanentUrl": "https://twitter.com/Hy_Purr_liquid/status/1870298558425170270",
    "hashtags": []
  },
  {
    "id": "1870266686882054220",
    "text": "@metaversejoji Didn't effect my bags https://t.co/NIpKVwQN6M",
    "username": "Hy_Purr_liquid",
    "timestamp": 1734741300000,
    "createdAt": "2024-12-21T00:35:00.000Z",
    "isReply": true,
    "isRetweet": false,
    "likes": 2,
    "retweetCount": 0,
    "replies": 0,
    "photos": [
      {
        "id": "1870266629692837888",
        "url": "https://pbs.twimg.com/media/GfSFlzIb0AA4RIn.jpg"
      }
    ],
    "videos": [],
    "urls": [],
    "permanentUrl": "https://twitter.com/Hy_Purr_liquid/status/1870266686882054220",
    "inReplyToStatusId": "1869817984426119297",
    "hashtags": []
  },
  {
    "id": "1870265945933128028",
    "text": "The Hyperliquid treasury is now worth $330million dollars. \nThey had $40million USDC on TGE\nThey've 8xd their treasury in 3 weeks.\nIt perpetually buys $hype, will be worth $1billion next year. https://t.co/7n5mmSa1BA",
    "username": "Hy_Purr_liquid",
    "timestamp": 1734741124000,
    "createdAt": "2024-12-21T00:32:04.000Z",
    "isReply": false,
    "isRetweet": false,
    "likes": 262,
    "retweetCount": 29,
    "replies": 22,
    "photos": [
      {
        "id": "1870265162458116098",
        "url": "https://pbs.twimg.com/media/GfSEQZQasAI8u7Z.jpg"
      }
    ],
    "videos": [],
    "urls": [],
    "permanentUrl": "https://twitter.com/Hy_Purr_liquid/status/1870265945933128028",
    "hashtags": []
  }
]